geoflow/__init__.py
geoflow/core/__init__.py
geoflow/core/pipeline.py
geoflow/core/provenance.py
geoflow/core/task.py
geoflow/crs/__init__.py
geoflow/crs/manager.py
geoflow/io/__init__.py
geoflow/io/loaders.py
geoflow/spatial/__init__.py
geoflow/spatial/operations.py
geoflow/validation/__init__.py
geoflow/validation/geometry.py
provflow-0.1.0.dist-info/licenses/LICENSE
provflow-0.1.0.dist-info/METADATA
provflow-0.1.0.dist-info/WHEEL
provflow-0.1.0.dist-info/top_level.txt
provflow-0.1.0.dist-info/RECORD
