Metadata-Version: 2.4
Name: provflow
Version: 0.1.0
Summary: Reproducible geospatial analysis framework with provenance tracking and CRS safety
Author-email: Senthil Kirthieswar <senthilarun08@gmail.com>
License: MIT
Project-URL: Homepage, https://github.com/SenthilArun8/pyGeoflow
Project-URL: Documentation, https://github.com/SenthilArun8/pyGeoflow#readme
Project-URL: Repository, https://github.com/SenthilArun8/pyGeoflow
Project-URL: Issues, https://github.com/SenthilArun8/pyGeoflow/issues
Project-URL: Changelog, https://github.com/SenthilArun8/pyGeoflow/blob/main/CHANGELOG.md
Keywords: gis,geospatial,geopandas,crs,coordinate-reference-system,spatial-analysis,geometry-validation,pipeline,reproducibility
Classifier: Development Status :: 3 - Alpha
Classifier: Intended Audience :: Science/Research
Classifier: Intended Audience :: Developers
Classifier: Programming Language :: Python :: 3
Classifier: Programming Language :: Python :: 3.9
Classifier: Programming Language :: Python :: 3.10
Classifier: Programming Language :: Python :: 3.11
Classifier: Programming Language :: Python :: 3.12
Classifier: Programming Language :: Python :: 3.13
Classifier: Topic :: Scientific/Engineering :: GIS
Classifier: Topic :: Software Development :: Libraries :: Python Modules
Classifier: Operating System :: OS Independent
Requires-Python: >=3.9
License-File: LICENSE
Requires-Dist: geopandas>=0.14.0
Requires-Dist: shapely>=2.0.0
Requires-Dist: pyproj>=3.5.0
Requires-Dist: fiona>=1.9.0
Requires-Dist: networkx>=3.0
Requires-Dist: pydantic>=2.0.0
Requires-Dist: loguru>=0.7.0
Provides-Extra: dev
Requires-Dist: pytest>=7.0.0; extra == "dev"
Requires-Dist: pytest-cov>=4.0.0; extra == "dev"
Requires-Dist: pytest-benchmark>=4.0.0; extra == "dev"
Requires-Dist: hypothesis>=6.70.0; extra == "dev"
Requires-Dist: black>=23.0.0; extra == "dev"
Requires-Dist: ruff>=0.1.0; extra == "dev"
Requires-Dist: mypy>=1.0.0; extra == "dev"
Requires-Dist: ipython>=8.0.0; extra == "dev"
Requires-Dist: jupyter>=1.0.0; extra == "dev"
Dynamic: license-file
